tagging_index/__init__.py
tagging_index/_udf/__init__.py
tagging_index/_udf/tag_converter.py
tagging_index/_udf/tag_matcher.py
tagging_index/_udf/udf_match_tag.py
tagging_index/data_generator/__init__.py
tagging_index/data_generator/databoard_ads_generator.py
tagging_index/data_generator/panel_data_generator.py
tagging_index/index_generator/__init__.py
tagging_index/index_generator/common_index_generator.py
tagging_index/index_generator/demand_index_generator.py
tagging_index/index_generator/general_index_generator.py
tagging_index/index_generator/index_intersection.py
tagging_index/index_generator/innovation_index_generator.py
tagging_index/index_generator/talent_index_generator.py
tagging_index/maxcompute/udf_release.py
tagging_index/schemas/json/index-tag-schema.json
tagging_index/tag_processor/__init__.py
tagging_index/tag_processor/tag_processor.py
tagging_index/tag_processor/tag_validator.py
tagging_index/utils/tag_tree.py
tagging_index-0.0.5.dist-info/METADATA
tagging_index-0.0.5.dist-info/WHEEL
tagging_index-0.0.5.dist-info/top_level.txt
tagging_index-0.0.5.dist-info/RECORD
