Metadata-Version: 2.1
Name: tagging-index
Version: 0.0.5
Summary: content tagging and index generator with maxcompute
Home-page: https://github.com/Digital-Transformation-Research-Center/tagging-index
Author: t2wei
Author-email: t2wei@me.com
Classifier: Programming Language :: Python :: 3
Classifier: License :: OSI Approved :: MIT License
Classifier: Operating System :: OS Independent
Requires-Python: >=3.7
Requires-Dist: treelib >=1.7.0
Requires-Dist: data2cloud >=0.0.2
